hf_mirror_downloader/__init__.py
hf_mirror_downloader/cli.py
hf_mirror_downloader/core.py
hf_mirror_downloader-0.2.0.dist-info/licenses/LICENSE
hf_mirror_downloader-0.2.0.dist-info/METADATA
hf_mirror_downloader-0.2.0.dist-info/WHEEL
hf_mirror_downloader-0.2.0.dist-info/entry_points.txt
hf_mirror_downloader-0.2.0.dist-info/top_level.txt
hf_mirror_downloader-0.2.0.dist-info/RECORD
