Metadata-Version: 2.4
Name: hf_mirror_downloader
Version: 0.2.0
Summary: Use HF mirror to download models with huggingface-cli
Author-email: Kang Bo <532910708@qq.com>
Requires-Python: >=3.7
License-File: LICENSE
Requires-Dist: transformers
Dynamic: license-file
